lentezinha/__init__.py
lentezinha/lens.py
lentezinha-0.1.0.dist-info/licenses/LICENSE
lentezinha-0.1.0.dist-info/METADATA
lentezinha-0.1.0.dist-info/WHEEL
lentezinha-0.1.0.dist-info/top_level.txt
lentezinha-0.1.0.dist-info/RECORD
