Metadata-Version: 2.4
Name: lentezinha
Version: 0.1.0
Summary: Tiny Lens (AKA 'lentezinha' in pt-BR) for nested dicts in Python
Author-email: Ivan Ramos Pagnossin <ivan.pagnossin@gmail.com>
License-Expression: MIT
Project-URL: Homepage, https://github.com/irpagnossin/lentezinha
Classifier: Programming Language :: Python :: 3.11
Classifier: Operating System :: OS Independent
Requires-Python: >=3.11
License-File: LICENSE
Requires-Dist: pydantic>=2.11.7
Dynamic: license-file
